meteocat_api_client/__init__.py
meteocat_api_client/excepcions.py
meteocat_api_client/connexio/__init__.py
meteocat_api_client/connexio/connexio.py
meteocat_api_client/connexio/memoria_cau.py
meteocat_api_client/helpers/utils.py
meteocat_api_client/helpers/validadors.py
meteocat_api_client/xarxes/__init__.py
meteocat_api_client/xarxes/base.py
meteocat_api_client/xarxes/quotes.py
meteocat_api_client/xarxes/referencia.py
meteocat_api_client/xarxes/xdde.py
meteocat_api_client/xarxes/pronostic/__init__.py
meteocat_api_client/xarxes/pronostic/pirineu.py
meteocat_api_client/xarxes/pronostic/platges.py
meteocat_api_client/xarxes/pronostic/prediccio.py
meteocat_api_client/xarxes/pronostic/pronostic.py
meteocat_api_client/xarxes/pronostic/smp.py
meteocat_api_client/xarxes/pronostic/uvi.py
meteocat_api_client/xarxes/xema/__init__.py
meteocat_api_client/xarxes/xema/auxiliars.py
meteocat_api_client/xarxes/xema/calcul_multivariable.py
meteocat_api_client/xarxes/xema/estacions.py
meteocat_api_client/xarxes/xema/estadistics.py
meteocat_api_client/xarxes/xema/mesurades.py
meteocat_api_client/xarxes/xema/representatives.py
meteocat_api_client/xarxes/xema/xema.py
meteocat_api_client-0.1.0.dist-info/LICENSE
meteocat_api_client-0.1.0.dist-info/METADATA
meteocat_api_client-0.1.0.dist-info/WHEEL
meteocat_api_client-0.1.0.dist-info/top_level.txt
meteocat_api_client-0.1.0.dist-info/RECORD
