Metadata-Version: 2.1
Name: meteocat-api-client
Version: 0.1.0
Summary: Client que consumeix dades de l'API REST del Servei Meteorològic de Catalunya
Home-page: https://github.com/herrera-lu/meteocat-api-client
Author: Lluís Herrera
Author-email: soluciona.cat@outlook.com
License: MIT
Platform: UNKNOWN
Classifier: Development Status :: 3 - Alpha
Classifier: Intended Audience :: Science/Research
Classifier: License :: OSI Approved :: MIT License
Classifier: Operating System :: OS Independent
Classifier: Programming Language :: Python :: 3
Classifier: Programming Language :: Python :: 3.6
Classifier: Programming Language :: Python :: 3.7
Classifier: Programming Language :: Python :: 3.8
Classifier: Programming Language :: Python :: 3.9
Classifier: Programming Language :: Python :: 3.10
Requires-Dist: requests-cache (>=0.9.3)
Requires-Dist: requests (>=2.27.1)
Requires-Dist: wheel (>=0.37.1)
